pyadic/__init__.py
pyadic/field_extension.py
pyadic/finite_field.py
pyadic/gaussian_rationals.py
pyadic/interpolation.py
pyadic/padic.py
pyadic/primes.py
pyadic/version.py
pyadic-0.2.4.dist-info/LICENSE.txt
pyadic-0.2.4.dist-info/METADATA
pyadic-0.2.4.dist-info/WHEEL
pyadic-0.2.4.dist-info/top_level.txt
pyadic-0.2.4.dist-info/RECORD
