Metadata-Version: 2.1
Name: pyadic
Version: 0.2.4
Summary: p-Adic numbers and finite fields in Python
Home-page: https://github.com/GDeLaurentis/pyadic
Download-URL: https://github.com/GDeLaurentis/pyadic/archive/v0.2.4.tar.gz
Author: Giuseppe De Laurentis
Author-email: g.dl@hotmail.it
License: GNU General Public License v3.0
Project-URL: Documentation, https://gdelaurentis.github.io/pyadic/
Project-URL: Issues, https://github.com/GDeLaurentis/pyadic/issues
Keywords: p-adic numbers,finite-fields,rational reconstruction
Classifier: Development Status :: 4 - Beta
Classifier: Intended Audience :: Science/Research
Classifier: Topic :: Scientific/Engineering :: Physics
Classifier: License :: OSI Approved :: GNU General Public License v3 (GPLv3)
Classifier: Programming Language :: Python :: 3.9
Classifier: Programming Language :: Python :: 3.10
Classifier: Programming Language :: Python :: 3.11
Classifier: Programming Language :: Python :: 3.12
Classifier: Programming Language :: Python :: 3.13
License-File: LICENSE.txt
Requires-Dist: numpy
Requires-Dist: sympy
